easyfermi/__init__.py
easyfermi/easyfermi.py
easyfermi/resources/ebl/ebl_dominguez11.fits.gz
easyfermi/resources/ebl/ebl_franceschini.fits.gz
easyfermi/resources/ebl/ebl_franceschini_2017.fits.gz
easyfermi/resources/ebl/ebl_saldana-lopez_2021.fits.gz
easyfermi/resources/ebl/frd_abs.fits.gz
easyfermi/resources/images/download_logo.png
easyfermi/resources/images/easyFermiIcon.png
easyfermi/resources/images/easyFermiWindow.png
easyfermi/resources/images/fermi.png
easyfermi-2.0.19.dist-info/LICENSE.txt
easyfermi-2.0.19.dist-info/METADATA
easyfermi-2.0.19.dist-info/WHEEL
easyfermi-2.0.19.dist-info/top_level.txt
easyfermi-2.0.19.dist-info/RECORD
