Metadata-Version: 2.1
Name: easyfermi
Version: 2.0.19
Summary: The easiest way to analyze Fermi-LAT data
Author: Raniere de Menezes
Author-email: <easyfermi@gmail.com>
Keywords: python,fermi,GUI,graphical interface,easyfermi,gamma-rays
Classifier: Development Status :: 5 - Production/Stable
Classifier: Intended Audience :: Science/Research
Classifier: Programming Language :: Python :: 3
Classifier: Operating System :: Unix
Classifier: Operating System :: MacOS :: MacOS X
License-File: LICENSE.txt
